clewsy/__init__.py
clewsy/cli.py
clewsy/skeleton.py
clewsy/model_building/BuildCLEWsModel.py
clewsy/model_building/Create_Energy_Set.py
clewsy/model_building/Fill_Empty_Sets.py
clewsy/model_building/UpdateMoManI.py
clewsy/model_building/Updateotoole.py
clewsy/model_building/__init__.py
clewsy/model_building/build.py
clewsy/model_building/model_building.py
clewsy-0.2.2.dist-info/AUTHORS.rst
clewsy-0.2.2.dist-info/LICENSE
clewsy-0.2.2.dist-info/LICENSE.txt
clewsy-0.2.2.dist-info/METADATA
clewsy-0.2.2.dist-info/WHEEL
clewsy-0.2.2.dist-info/entry_points.txt
clewsy-0.2.2.dist-info/top_level.txt
clewsy-0.2.2.dist-info/RECORD
