Metadata-Version: 2.1
Name: clewsy
Version: 0.2.2
Summary: clewsy - A set of tools for building CLEWs models.
Home-page: https://github.com/OSeMOSYS/clewsy
Author: Taco Niet
Author-email: Taco_Niet@sfu.ca
License: mit
Project-URL: Documentation, https://github.com/OSeMOSYS/clewsy
Platform: any
Classifier: Development Status :: 4 - Beta
Classifier: Programming Language :: Python
Requires-Dist: pyyaml
Requires-Dist: pymongo
Requires-Dist: colorama
Provides-Extra: testing
Requires-Dist: pytest ; extra == 'testing'
Requires-Dist: pytest-cov ; extra == 'testing'
